WeightMatrix_Analysis/__init__.py
WeightMatrix_Analysis/main.py
WeightMatrix_Analysis-0.1.5.dist-info/LICENSE
WeightMatrix_Analysis-0.1.5.dist-info/METADATA
WeightMatrix_Analysis-0.1.5.dist-info/WHEEL
WeightMatrix_Analysis-0.1.5.dist-info/entry_points.txt
WeightMatrix_Analysis-0.1.5.dist-info/top_level.txt
WeightMatrix_Analysis-0.1.5.dist-info/RECORD
