Metadata-Version: 2.1
Name: WeightMatrix_Analysis
Version: 0.1.5
License-File: LICENSE
Requires-Dist: numpy
Requires-Dist: scipy
